streamyt/__main__.py
streamyt-1.1.0.dist-info/METADATA
streamyt-1.1.0.dist-info/WHEEL
streamyt-1.1.0.dist-info/entry_points.txt
streamyt-1.1.0.dist-info/top_level.txt
streamyt-1.1.0.dist-info/RECORD
