Metadata-Version: 2.1
Name: streamyt
Version: 1.1.0
Summary: Search and stream videos from Youtube
Home-page: https://github.com/sAksham-Ar/ytstreamer
Author: Saksham Arya
Author-email: aryasaksham@gmail.com
License: GPLv3
Platform: UNKNOWN
Classifier: License :: OSI Approved :: GNU General Public License v3 (GPLv3)
Classifier: Programming Language :: Python :: 3
Classifier: Programming Language :: Python :: 3.8
Requires-Dist: bs4
Requires-Dist: requests
